CHANGELOG.txt
LICENSE.txt
MANIFEST.in
README.txt
piglow.py
setup.py
piglow.egg-info/PKG-INFO
piglow.egg-info/SOURCES.txt
piglow.egg-info/dependency_links.txt
piglow.egg-info/requires.txt
piglow.egg-info/top_level.txt
test/test.py