Metadata-Version: 1.1
Name: piglow
Version: 1.2.4
Summary: A module to drive the Pimoroni PiGlow board, based on the sn3218 i2c LED controller
Home-page: http://www.pimoroni.com
Author: Philip Howard
Author-email: phil@pimoroni.com
License: MIT
Keywords: Raspberry Pi sn3218 PiGlow i2c
Platform: UNKNOWN
Classifier: Development Status :: 5 - Production/Stable
Classifier: Operating System :: POSIX :: Linux
Classifier: License :: OSI Approved :: MIT License
Classifier: Intended Audience :: Developers
Classifier: Programming Language :: Python :: 2.6
Classifier: Programming Language :: Python :: 2.7
Classifier: Programming Language :: Python :: 3
Classifier: Topic :: Software Development
Classifier: Topic :: System :: Hardware
